[{"id":94,"name":"gengar","stats":{"hp":60,"attack":65,"defense":60,"special-attack":130,"special-defense":75,"speed":110},"raidMoves":["shadow-ball","sludge-bomb","dazzling-gleam","will-o-wisp"],"types":["ghost","poison"],"moveInfo":[{"name":"shadow-ball","power":80,"type":"ghost","class":"special"},{"name":"sludge-bomb","power":90,"type":"poison","class":"special"},{"name":"dazzling-gleam","power":80,"type":"fairy","class":"special"},{"name":"will-o-wisp","power":null,"type":"fire","class":"status"}]},{"id":132,"name":"ditto","stats":{"hp":48,"attack":48,"defense":48,"special-attack":48,"special-defense":48,"speed":48},"raidMoves":["transform"],"types":["normal"],"moveInfo":[{"name":"transform","power":null,"type":"normal","class":"status"}]},{"id":128,"name":"tauros","stats":{"hp":75,"attack":100,"defense":95,"special-attack":40,"special-defense":70,"speed":110},"raidMoves":["close-combat","thrash","zen-headbutt","raging-bull"],"types":["normal"],"moveInfo":[{"name":"close-combat","power":120,"type":"fighting","class":"physical"},{"name":"thrash","power":120,"type":"normal","class":"physical"},{"name":"zen-headbutt","power":80,"type":"psychic","class":"physical"},{"name":"raging-bull","power":90,"type":"normal","class":"physical"}]},{"id":130,"name":"gyarados","stats":{"hp":95,"attack":125,"defense":79,"special-attack":60,"special-defense":100,"speed":81},"raidMoves":["aqua-tail","crunch","hurricane","ice-fang"],"types":["water","flying"],"moveInfo":[{"name":"aqua-tail","power":90,"type":"water","class":"physical"},{"name":"crunch","power":80,"type":"dark","class":"physical"},{"name":"hurricane","power":110,"type":"flying","class":"special"},{"name":"ice-fang","power":65,"type":"ice","class":"physical"}]},{"id":134,"name":"vaporeon","stats":{"hp":130,"attack":65,"defense":60,"special-attack":110,"special-defense":95,"speed":65},"raidMoves":["tera-blast","surf","hyper-voice","yawn"],"types":["water"],"moveInfo":[{"name":"tera-blast","power":80,"type":"normal","class":"special"},{"name":"surf","power":90,"type":"water","class":"special"},{"name":"hyper-voice","power":90,"type":"normal","class":"special"},{"name":"yawn","power":null,"type":"normal","class":"status"}]},{"id":135,"name":"jolteon","stats":{"hp":65,"attack":65,"defense":60,"special-attack":110,"special-defense":95,"speed":130},"raidMoves":["tera-blast","thunderbolt","shadow-ball","thunder-wave"],"types":["electric"],"moveInfo":[{"name":"tera-blast","power":80,"type":"normal","class":"special"},{"name":"thunderbolt","power":90,"type":"electric","class":"special"},{"name":"shadow-ball","power":80,"type":"ghost","class":"special"},{"name":"thunder-wave","power":null,"type":"electric","class":"status"}]},{"id":136,"name":"flareon","stats":{"hp":65,"attack":130,"defense":60,"special-attack":95,"special-defense":110,"speed":65},"raidMoves":["tera-blast","flare-blitz","lava-plume","will-o-wisp"],"types":["fire"],"moveInfo":[{"name":"tera-blast","power":80,"type":"normal","class":"special"},{"name":"flare-blitz","power":120,"type":"fire","class":"physical"},{"name":"lava-plume","power":80,"type":"fire","class":"special"},{"name":"will-o-wisp","power":null,"type":"fire","class":"status"}]},{"id":149,"name":"dragonite","stats":{"hp":91,"attack":134,"defense":95,"special-attack":100,"special-defense":100,"speed":80},"raidMoves":["dragon-rush","extreme-speed","dragon-dance","aqua-tail"],"types":["dragon","flying"],"moveInfo":[{"name":"dragon-rush","power":100,"type":"dragon","class":"physical"},{"name":"extreme-speed","power":80,"type":"normal","class":"physical"},{"name":"dragon-dance","power":null,"type":"dragon","class":"status"},{"name":"aqua-tail","power":90,"type":"water","class":"physical"}]},{"id":196,"name":"espeon","stats":{"hp":65,"attack":65,"defense":60,"special-attack":130,"special-defense":95,"speed":110},"raidMoves":["tera-blast","psychic","psyshock","tickle"],"types":["psychic"],"moveInfo":[{"name":"tera-blast","power":80,"type":"normal","class":"special"},{"name":"psychic","power":90,"type":"psychic","class":"special"},{"name":"psyshock","power":80,"type":"psychic","class":"special"},{"name":"tickle","power":null,"type":"normal","class":"status"}]},{"id":197,"name":"umbreon","stats":{"hp":95,"attack":65,"defense":110,"special-attack":60,"special-defense":130,"speed":65},"raidMoves":["tera-blast","dark-pulse","foul-play","tickle"],"types":["dark"],"moveInfo":[{"name":"tera-blast","power":80,"type":"normal","class":"special"},{"name":"dark-pulse","power":80,"type":"dark","class":"special"},{"name":"foul-play","power":95,"type":"dark","class":"physical"},{"name":"tickle","power":null,"type":"normal","class":"status"}]},{"id":199,"name":"slowking","stats":{"hp":95,"attack":75,"defense":80,"special-attack":100,"special-defense":110,"speed":30},"raidMoves":["surf","psyshock","trick-room","flamethrower"],"types":["water","psychic"],"moveInfo":[{"name":"surf","power":90,"type":"water","class":"special"},{"name":"psyshock","power":80,"type":"psychic","class":"special"},{"name":"trick-room","power":null,"type":"psychic","class":"status"},{"name":"flamethrower","power":90,"type":"fire","class":"special"}]},{"id":212,"name":"scizor","stats":{"hp":70,"attack":130,"defense":100,"special-attack":55,"special-defense":80,"speed":65},"raidMoves":["x-scissor","bullet-punch","close-combat","iron-head"],"types":["bug","steel"],"moveInfo":[{"name":"x-scissor","power":80,"type":"bug","class":"physical"},{"name":"bullet-punch","power":40,"type":"steel","class":"physical"},{"name":"close-combat","power":120,"type":"fighting","class":"physical"},{"name":"iron-head","power":80,"type":"steel","class":"physical"}]},{"id":214,"name":"heracross","stats":{"hp":80,"attack":125,"defense":75,"special-attack":40,"special-defense":95,"speed":85},"raidMoves":["megahorn","close-combat","thrash","leer"],"types":["bug","fighting"],"moveInfo":[{"name":"megahorn","power":120,"type":"bug","class":"physical"},{"name":"close-combat","power":120,"type":"fighting","class":"physical"},{"name":"thrash","power":120,"type":"normal","class":"physical"},{"name":"leer","power":null,"type":"normal","class":"status"}]},{"id":242,"name":"blissey","stats":{"hp":255,"attack":10,"defense":10,"special-attack":75,"special-defense":135,"speed":55},"raidMoves":["dazzling-gleam","hyper-voice","sing","light-screen"],"types":["normal"],"moveInfo":[{"name":"dazzling-gleam","power":80,"type":"fairy","class":"special"},{"name":"hyper-voice","power":90,"type":"normal","class":"special"},{"name":"sing","power":null,"type":"normal","class":"status"},{"name":"light-screen","power":null,"type":"psychic","class":"status"}]},{"id":248,"name":"tyranitar","stats":{"hp":100,"attack":134,"defense":110,"special-attack":95,"special-defense":100,"speed":61},"raidMoves":["stone-edge","crunch","screech","rock-blast"],"types":["rock","dark"],"moveInfo":[{"name":"stone-edge","power":100,"type":"rock","class":"physical"},{"name":"crunch","power":80,"type":"dark","class":"physical"},{"name":"screech","power":null,"type":"normal","class":"status"},{"name":"rock-blast","power":25,"type":"rock","class":"physical"}]},{"id":279,"name":"pelipper","stats":{"hp":60,"attack":50,"defense":100,"special-attack":95,"special-defense":70,"speed":65},"raidMoves":["hurricane","hydro-pump","mist","supersonic"],"types":["water","flying"],"moveInfo":[{"name":"hurricane","power":110,"type":"flying","class":"special"},{"name":"hydro-pump","power":110,"type":"water","class":"special"},{"name":"mist","power":null,"type":"ice","class":"status"},{"name":"supersonic","power":null,"type":"normal","class":"status"}]},{"id":282,"name":"gardevoir","stats":{"hp":68,"attack":65,"defense":65,"special-attack":125,"special-defense":115,"speed":80},"raidMoves":["moonblast","psychic","calm-mind","thunder-wave"],"types":["psychic","fairy"],"moveInfo":[{"name":"moonblast","power":95,"type":"fairy","class":"special"},{"name":"psychic","power":90,"type":"psychic","class":"special"},{"name":"calm-mind","power":null,"type":"psychic","class":"status"},{"name":"thunder-wave","power":null,"type":"electric","class":"status"}]},{"id":286,"name":"breloom","stats":{"hp":60,"attack":130,"defense":80,"special-attack":60,"special-defense":60,"speed":70},"raidMoves":["bullet-seed","low-sweep","spore","aerial-ace"],"types":["grass","fighting"],"moveInfo":[{"name":"bullet-seed","power":25,"type":"grass","class":"physical"},{"name":"low-sweep","power":65,"type":"fighting","class":"physical"},{"name":"spore","power":null,"type":"grass","class":"status"},{"name":"aerial-ace","power":60,"type":"flying","class":"physical"}]},{"id":324,"name":"torkoal","stats":{"hp":70,"attack":85,"defense":140,"special-attack":85,"special-defense":70,"speed":20},"raidMoves":["lava-plume","yawn","clear-smog","body-slam"],"types":["fire"],"moveInfo":[{"name":"lava-plume","power":80,"type":"fire","class":"special"},{"name":"yawn","power":null,"type":"normal","class":"status"},{"name":"clear-smog","power":50,"type":"poison","class":"special"},{"name":"body-slam","power":85,"type":"normal","class":"physical"}]},{"id":373,"name":"salamence","stats":{"hp":95,"attack":135,"defense":80,"special-attack":110,"special-defense":80,"speed":100},"raidMoves":["outrage","dual-wingbeat","flamethrower","tera-blast"],"types":["dragon","flying"],"moveInfo":[{"name":"outrage","power":120,"type":"dragon","class":"physical"},{"name":"dual-wingbeat","power":40,"type":"flying","class":"physical"},{"name":"flamethrower","power":90,"type":"fire","class":"special"},{"name":"tera-blast","power":80,"type":"normal","class":"special"}]},{"id":398,"name":"staraptor","stats":{"hp":85,"attack":120,"defense":70,"special-attack":50,"special-defense":60,"speed":100},"raidMoves":["close-combat","brave-bird","double-edge","feather-dance"],"types":["normal","flying"],"moveInfo":[{"name":"close-combat","power":120,"type":"fighting","class":"physical"},{"name":"brave-bird","power":120,"type":"flying","class":"physical"},{"name":"double-edge","power":120,"type":"normal","class":"physical"},{"name":"feather-dance","power":null,"type":"flying","class":"status"}]},{"id":445,"name":"garchomp","stats":{"hp":108,"attack":130,"defense":95,"special-attack":80,"special-defense":85,"speed":102},"raidMoves":["outrage","earthquake","flamethrower","rock-slide"],"types":["dragon","ground"],"moveInfo":[{"name":"outrage","power":120,"type":"dragon","class":"physical"},{"name":"earthquake","power":100,"type":"ground","class":"physical"},{"name":"flamethrower","power":90,"type":"fire","class":"special"},{"name":"rock-slide","power":75,"type":"rock","class":"physical"}]},{"id":450,"name":"hippowdon","stats":{"hp":108,"attack":112,"defense":118,"special-attack":68,"special-defense":72,"speed":47},"raidMoves":["earthquake","ice-fang","yawn","rock-slide"],"types":["ground"],"moveInfo":[{"name":"earthquake","power":100,"type":"ground","class":"physical"},{"name":"ice-fang","power":65,"type":"ice","class":"physical"},{"name":"yawn","power":null,"type":"normal","class":"status"},{"name":"rock-slide","power":75,"type":"rock","class":"physical"}]},{"id":462,"name":"magnezone","stats":{"hp":70,"attack":70,"defense":115,"special-attack":130,"special-defense":90,"speed":60},"raidMoves":["thunder","flash-cannon","tri-attack","thunder-wave"],"types":["electric","steel"],"moveInfo":[{"name":"thunder","power":110,"type":"electric","class":"special"},{"name":"flash-cannon","power":80,"type":"steel","class":"special"},{"name":"tri-attack","power":80,"type":"normal","class":"special"},{"name":"thunder-wave","power":null,"type":"electric","class":"status"}]},{"id":470,"name":"leafeon","stats":{"hp":65,"attack":110,"defense":130,"special-attack":60,"special-defense":65,"speed":95},"raidMoves":["tera-blast","leaf-blade","double-kick","charm"],"types":["grass"],"moveInfo":[{"name":"tera-blast","power":80,"type":"normal","class":"special"},{"name":"leaf-blade","power":90,"type":"grass","class":"physical"},{"name":"double-kick","power":30,"type":"fighting","class":"physical"},{"name":"charm","power":null,"type":"fairy","class":"status"}]},{"id":471,"name":"glaceon","stats":{"hp":65,"attack":60,"defense":110,"special-attack":130,"special-defense":95,"speed":65},"raidMoves":["tera-blast","ice-beam","blizzard","charm"],"types":["ice"],"moveInfo":[{"name":"tera-blast","power":80,"type":"normal","class":"special"},{"name":"ice-beam","power":90,"type":"ice","class":"special"},{"name":"blizzard","power":110,"type":"ice","class":"special"},{"name":"charm","power":null,"type":"fairy","class":"status"}]},{"id":475,"name":"gallade","stats":{"hp":68,"attack":125,"defense":65,"special-attack":65,"special-defense":115,"speed":80},"raidMoves":["psycho-cut","close-combat","will-o-wisp","aerial-ace"],"types":["psychic","fighting"],"moveInfo":[{"name":"psycho-cut","power":70,"type":"psychic","class":"physical"},{"name":"close-combat","power":120,"type":"fighting","class":"physical"},{"name":"will-o-wisp","power":null,"type":"fire","class":"status"},{"name":"aerial-ace","power":60,"type":"flying","class":"physical"}]},{"id":591,"name":"amoonguss","stats":{"hp":114,"attack":85,"defense":70,"special-attack":85,"special-defense":80,"speed":30},"raidMoves":["energy-ball","foul-play","spore","sludge-bomb"],"types":["grass","poison"],"moveInfo":[{"name":"energy-ball","power":90,"type":"grass","class":"special"},{"name":"foul-play","power":95,"type":"dark","class":"physical"},{"name":"spore","power":null,"type":"grass","class":"status"},{"name":"sludge-bomb","power":90,"type":"poison","class":"special"}]},{"id":612,"name":"haxorus","stats":{"hp":76,"attack":147,"defense":90,"special-attack":60,"special-defense":70,"speed":97},"raidMoves":["outrage","crunch","giga-impact","first-impression"],"types":["dragon"],"moveInfo":[{"name":"outrage","power":120,"type":"dragon","class":"physical"},{"name":"crunch","power":80,"type":"dark","class":"physical"},{"name":"giga-impact","power":150,"type":"normal","class":"physical"},{"name":"first-impression","power":90,"type":"bug","class":"physical"}]},{"id":635,"name":"hydreigon","stats":{"hp":92,"attack":105,"defense":90,"special-attack":125,"special-defense":90,"speed":98},"raidMoves":["dark-pulse","dragon-pulse","crunch","taunt"],"types":["dark","dragon"],"moveInfo":[{"name":"dark-pulse","power":80,"type":"dark","class":"special"},{"name":"dragon-pulse","power":85,"type":"dragon","class":"special"},{"name":"crunch","power":80,"type":"dark","class":"physical"},{"name":"taunt","power":null,"type":"dark","class":"status"}]},{"id":637,"name":"volcarona","stats":{"hp":85,"attack":60,"defense":65,"special-attack":135,"special-defense":105,"speed":100},"raidMoves":["bug-buzz","flamethrower","hurricane","tailwind"],"types":["bug","fire"],"moveInfo":[{"name":"bug-buzz","power":90,"type":"bug","class":"special"},{"name":"flamethrower","power":90,"type":"fire","class":"special"},{"name":"hurricane","power":110,"type":"flying","class":"special"},{"name":"tailwind","power":null,"type":"flying","class":"status"}]},{"id":663,"name":"talonflame","stats":{"hp":78,"attack":81,"defense":71,"special-attack":74,"special-defense":69,"speed":126},"raidMoves":["brave-bird","flare-blitz","flamethrower","tera-blast"],"types":["fire","flying"],"moveInfo":[{"name":"brave-bird","power":120,"type":"flying","class":"physical"},{"name":"flare-blitz","power":120,"type":"fire","class":"physical"},{"name":"flamethrower","power":90,"type":"fire","class":"special"},{"name":"tera-blast","power":80,"type":"normal","class":"special"}]},{"id":691,"name":"dragalge","stats":{"hp":65,"attack":75,"defense":90,"special-attack":97,"special-defense":123,"speed":44},"raidMoves":["dragon-pulse","sludge-bomb","water-pulse","toxic"],"types":["poison","dragon"],"moveInfo":[{"name":"dragon-pulse","power":85,"type":"dragon","class":"special"},{"name":"sludge-bomb","power":90,"type":"poison","class":"special"},{"name":"water-pulse","power":60,"type":"water","class":"special"},{"name":"toxic","power":null,"type":"poison","class":"status"}]},{"id":693,"name":"clawitzer","stats":{"hp":71,"attack":73,"defense":88,"special-attack":120,"special-defense":89,"speed":59},"raidMoves":["water-pulse","dragon-pulse","aura-sphere","crabhammer"],"types":["water"],"moveInfo":[{"name":"water-pulse","power":60,"type":"water","class":"special"},{"name":"dragon-pulse","power":85,"type":"dragon","class":"special"},{"name":"aura-sphere","power":80,"type":"fighting","class":"special"},{"name":"crabhammer","power":100,"type":"water","class":"physical"}]},{"id":700,"name":"sylveon","stats":{"hp":95,"attack":65,"defense":65,"special-attack":110,"special-defense":130,"speed":60},"raidMoves":["tera-blast","hyper-voice","moonblast","yawn"],"types":["fairy"],"moveInfo":[{"name":"tera-blast","power":80,"type":"normal","class":"special"},{"name":"hyper-voice","power":90,"type":"normal","class":"special"},{"name":"moonblast","power":95,"type":"fairy","class":"special"},{"name":"yawn","power":null,"type":"normal","class":"status"}]},{"id":706,"name":"goodra","stats":{"hp":90,"attack":100,"defense":70,"special-attack":110,"special-defense":150,"speed":80},"raidMoves":["dragon-pulse","surf","sludge-bomb","power-whip"],"types":["dragon"],"moveInfo":[{"name":"dragon-pulse","power":85,"type":"dragon","class":"special"},{"name":"surf","power":90,"type":"water","class":"special"},{"name":"sludge-bomb","power":90,"type":"poison","class":"special"},{"name":"power-whip","power":120,"type":"grass","class":"physical"}]},{"id":713,"name":"avalugg","stats":{"hp":95,"attack":117,"defense":184,"special-attack":44,"special-defense":46,"speed":28},"raidMoves":["icicle-crash","heavy-slam","snowscape","ice-spinner"],"types":["ice"],"moveInfo":[{"name":"icicle-crash","power":85,"type":"ice","class":"physical"},{"name":"heavy-slam","power":null,"type":"steel","class":"physical"},{"name":"snowscape","power":0,"type":"ice","class":"status"},{"name":"ice-spinner","power":80,"type":"ice","class":"physical"}]},{"id":745,"name":"lycanroc-midday","stats":{"hp":75,"attack":115,"defense":65,"special-attack":55,"special-defense":65,"speed":112},"raidMoves":["accelerock","rock-slide","crunch","taunt"],"types":["rock"],"moveInfo":[{"name":"accelerock","power":40,"type":"rock","class":"physical"},{"name":"rock-slide","power":75,"type":"rock","class":"physical"},{"name":"crunch","power":80,"type":"dark","class":"physical"},{"name":"taunt","power":null,"type":"dark","class":"status"}]},{"id":748,"name":"toxapex","stats":{"hp":50,"attack":63,"defense":152,"special-attack":53,"special-defense":142,"speed":35},"raidMoves":["water-pulse","liquidation","poison-jab","pin-missile"],"types":["poison","water"],"moveInfo":[{"name":"water-pulse","power":60,"type":"water","class":"special"},{"name":"liquidation","power":85,"type":"water","class":"physical"},{"name":"poison-jab","power":80,"type":"poison","class":"physical"},{"name":"pin-missile","power":25,"type":"bug","class":"physical"}]},{"id":778,"name":"mimikyu-disguised","stats":{"hp":55,"attack":90,"defense":80,"special-attack":50,"special-defense":105,"speed":96},"raidMoves":["play-rough","shadow-claw","shadow-sneak","wood-hammer"],"types":["ghost","fairy"],"moveInfo":[{"name":"play-rough","power":90,"type":"fairy","class":"physical"},{"name":"shadow-claw","power":70,"type":"ghost","class":"physical"},{"name":"shadow-sneak","power":40,"type":"ghost","class":"physical"},{"name":"wood-hammer","power":120,"type":"grass","class":"physical"}]},{"id":823,"name":"corviknight","stats":{"hp":98,"attack":87,"defense":105,"special-attack":53,"special-defense":85,"speed":67},"raidMoves":["iron-head","drill-peck","body-press","hone-claws"],"types":["flying","steel"],"moveInfo":[{"name":"iron-head","power":80,"type":"steel","class":"physical"},{"name":"drill-peck","power":80,"type":"flying","class":"physical"},{"name":"body-press","power":80,"type":"fighting","class":"physical"},{"name":"hone-claws","power":null,"type":"dark","class":"status"}]},{"id":871,"name":"pincurchin","stats":{"hp":48,"attack":101,"defense":95,"special-attack":91,"special-defense":85,"speed":15},"raidMoves":["zing-zap","thunder","surf","poison-jab"],"types":["electric"],"moveInfo":[{"name":"zing-zap","power":80,"type":"electric","class":"physical"},{"name":"thunder","power":110,"type":"electric","class":"special"},{"name":"surf","power":90,"type":"water","class":"special"},{"name":"poison-jab","power":80,"type":"poison","class":"physical"}]},{"id":873,"name":"frosmoth","stats":{"hp":70,"attack":65,"defense":60,"special-attack":125,"special-defense":90,"speed":65},"raidMoves":["blizzard","bug-buzz","hurricane","snowscape"],"types":["ice","bug"],"moveInfo":[{"name":"blizzard","power":110,"type":"ice","class":"special"},{"name":"bug-buzz","power":90,"type":"bug","class":"special"},{"name":"hurricane","power":110,"type":"flying","class":"special"},{"name":"snowscape","power":0,"type":"ice","class":"status"}]},{"id":887,"name":"dragapult","stats":{"hp":88,"attack":120,"defense":75,"special-attack":100,"special-defense":75,"speed":142},"raidMoves":["shadow-ball","dragon-pulse","thunderbolt","flamethrower"],"types":["dragon","ghost"],"moveInfo":[{"name":"shadow-ball","power":80,"type":"ghost","class":"special"},{"name":"dragon-pulse","power":85,"type":"dragon","class":"special"},{"name":"thunderbolt","power":90,"type":"electric","class":"special"},{"name":"flamethrower","power":90,"type":"fire","class":"special"}]},{"id":923,"name":"pawmot","stats":{"hp":70,"attack":115,"defense":70,"special-attack":70,"special-defense":60,"speed":105},"raidMoves":["wild-charge","close-combat","double-shock","nuzzle"],"types":["electric","fighting"],"moveInfo":[{"name":"wild-charge","power":90,"type":"electric","class":"physical"},{"name":"close-combat","power":120,"type":"fighting","class":"physical"},{"name":"double-shock","power":120,"type":"electric","class":"physical"},{"name":"nuzzle","power":20,"type":"electric","class":"physical"}]},{"id":925,"name":"maushold","stats":{"hp":74,"attack":75,"defense":70,"special-attack":65,"special-defense":75,"speed":111},"raidMoves":["play-rough","take-down","low-kick","charm"],"types":["normal"],"moveInfo":[{"name":"play-rough","power":90,"type":"fairy","class":"physical"},{"name":"take-down","power":90,"type":"normal","class":"physical"},{"name":"low-kick","power":null,"type":"fighting","class":"physical"},{"name":"charm","power":null,"type":"fairy","class":"status"}]},{"id":927,"name":"dachsbun","stats":{"hp":57,"attack":80,"defense":115,"special-attack":50,"special-defense":80,"speed":95},"raidMoves":["play-rough","double-edge","bite","baby-doll-eyes"],"types":["fairy"],"moveInfo":[{"name":"play-rough","power":90,"type":"fairy","class":"physical"},{"name":"double-edge","power":120,"type":"normal","class":"physical"},{"name":"bite","power":60,"type":"dark","class":"physical"},{"name":"baby-doll-eyes","power":null,"type":"fairy","class":"status"}]},{"id":934,"name":"garganacl","stats":{"hp":100,"attack":100,"defense":130,"special-attack":45,"special-defense":90,"speed":35},"raidMoves":["stone-edge","heavy-slam","salt-cure","hammer-arm"],"types":["rock"],"moveInfo":[{"name":"stone-edge","power":100,"type":"rock","class":"physical"},{"name":"heavy-slam","power":null,"type":"steel","class":"physical"},{"name":"salt-cure","power":40,"type":"rock","class":"physical"},{"name":"hammer-arm","power":100,"type":"fighting","class":"physical"}]},{"id":936,"name":"armarouge","stats":{"hp":85,"attack":60,"defense":100,"special-attack":125,"special-defense":80,"speed":75},"raidMoves":["armor-cannon","psychic","night-shade","will-o-wisp"],"types":["fire","psychic"],"moveInfo":[{"name":"armor-cannon","power":120,"type":"fire","class":"special"},{"name":"psychic","power":90,"type":"psychic","class":"special"},{"name":"night-shade","power":null,"type":"ghost","class":"special"},{"name":"will-o-wisp","power":null,"type":"fire","class":"status"}]},{"id":937,"name":"ceruledge","stats":{"hp":75,"attack":125,"defense":80,"special-attack":60,"special-defense":100,"speed":85},"raidMoves":["bitter-blade","shadow-claw","psycho-cut","will-o-wisp"],"types":["fire","ghost"],"moveInfo":[{"name":"bitter-blade","power":90,"type":"fire","class":"physical"},{"name":"shadow-claw","power":70,"type":"ghost","class":"physical"},{"name":"psycho-cut","power":70,"type":"psychic","class":"physical"},{"name":"will-o-wisp","power":null,"type":"fire","class":"status"}]},{"id":941,"name":"kilowattrel","stats":{"hp":70,"attack":70,"defense":60,"special-attack":105,"special-defense":60,"speed":125},"raidMoves":["hurricane","thunder","uproar","scary-face"],"types":["electric","flying"],"moveInfo":[{"name":"hurricane","power":110,"type":"flying","class":"special"},{"name":"thunder","power":110,"type":"electric","class":"special"},{"name":"uproar","power":90,"type":"normal","class":"special"},{"name":"scary-face","power":null,"type":"normal","class":"status"}]},{"id":943,"name":"mabosstiff","stats":{"hp":80,"attack":120,"defense":90,"special-attack":60,"special-defense":70,"speed":85},"raidMoves":["crunch","reversal","outrage","take-down"],"types":["dark"],"moveInfo":[{"name":"crunch","power":80,"type":"dark","class":"physical"},{"name":"reversal","power":null,"type":"fighting","class":"physical"},{"name":"outrage","power":120,"type":"dragon","class":"physical"},{"name":"take-down","power":90,"type":"normal","class":"physical"}]},{"id":945,"name":"grafaiai","stats":{"hp":63,"attack":95,"defense":65,"special-attack":80,"special-defense":72,"speed":110},"raidMoves":["knock-off","gunk-shot","take-down","flatter"],"types":["poison","normal"],"moveInfo":[{"name":"knock-off","power":65,"type":"dark","class":"physical"},{"name":"gunk-shot","power":120,"type":"poison","class":"physical"},{"name":"take-down","power":90,"type":"normal","class":"physical"},{"name":"flatter","power":null,"type":"dark","class":"status"}]},{"id":949,"name":"toedscruel","stats":{"hp":80,"attack":70,"defense":65,"special-attack":80,"special-defense":120,"speed":100},"raidMoves":["energy-ball","earth-power","spore","hex"],"types":["ground","grass"],"moveInfo":[{"name":"energy-ball","power":90,"type":"grass","class":"special"},{"name":"earth-power","power":90,"type":"ground","class":"special"},{"name":"spore","power":null,"type":"grass","class":"status"},{"name":"hex","power":65,"type":"ghost","class":"special"}]},{"id":950,"name":"klawf","stats":{"hp":70,"attack":100,"defense":115,"special-attack":35,"special-defense":55,"speed":75},"raidMoves":["stone-edge","rock-smash","x-scissor","sandstorm"],"types":["rock"],"moveInfo":[{"name":"stone-edge","power":100,"type":"rock","class":"physical"},{"name":"rock-smash","power":40,"type":"fighting","class":"physical"},{"name":"x-scissor","power":80,"type":"bug","class":"physical"},{"name":"sandstorm","power":null,"type":"rock","class":"status"}]},{"id":959,"name":"tinkaton","stats":{"hp":85,"attack":75,"defense":77,"special-attack":70,"special-defense":105,"speed":94},"raidMoves":["gigaton-hammer","play-rough","knock-off","thunder-wave"],"types":["fairy","steel"],"moveInfo":[{"name":"gigaton-hammer","power":160,"type":"steel","class":"physical"},{"name":"play-rough","power":90,"type":"fairy","class":"physical"},{"name":"knock-off","power":65,"type":"dark","class":"physical"},{"name":"thunder-wave","power":null,"type":"electric","class":"status"}]},{"id":962,"name":"bombirdier","stats":{"hp":70,"attack":103,"defense":85,"special-attack":60,"special-defense":85,"speed":82},"raidMoves":["rock-slide","acrobatics","knock-off","feather-dance"],"types":["flying","dark"],"moveInfo":[{"name":"rock-slide","power":75,"type":"rock","class":"physical"},{"name":"acrobatics","power":55,"type":"flying","class":"physical"},{"name":"knock-off","power":65,"type":"dark","class":"physical"},{"name":"feather-dance","power":null,"type":"flying","class":"status"}]},{"id":966,"name":"revavroom","stats":{"hp":80,"attack":119,"defense":90,"special-attack":54,"special-defense":67,"speed":90},"raidMoves":["gunk-shot","overheat","iron-head","taunt"],"types":["steel","poison"],"moveInfo":[{"name":"gunk-shot","power":120,"type":"poison","class":"physical"},{"name":"overheat","power":130,"type":"fire","class":"special"},{"name":"iron-head","power":80,"type":"steel","class":"physical"},{"name":"taunt","power":null,"type":"dark","class":"status"}]},{"id":967,"name":"cyclizar","stats":{"hp":70,"attack":95,"defense":65,"special-attack":85,"special-defense":65,"speed":121},"raidMoves":["double-edge","dragon-claw","dragon-pulse","knock-off"],"types":["dragon","normal"],"moveInfo":[{"name":"double-edge","power":120,"type":"normal","class":"physical"},{"name":"dragon-claw","power":80,"type":"dragon","class":"physical"},{"name":"dragon-pulse","power":85,"type":"dragon","class":"special"},{"name":"knock-off","power":65,"type":"dark","class":"physical"}]},{"id":968,"name":"orthworm","stats":{"hp":70,"attack":85,"defense":145,"special-attack":60,"special-defense":55,"speed":65},"raidMoves":["iron-head","earthquake","smack-down","sandstorm"],"types":["steel"],"moveInfo":[{"name":"iron-head","power":80,"type":"steel","class":"physical"},{"name":"earthquake","power":100,"type":"ground","class":"physical"},{"name":"smack-down","power":50,"type":"rock","class":"physical"},{"name":"sandstorm","power":null,"type":"rock","class":"status"}]},{"id":970,"name":"glimmora","stats":{"hp":83,"attack":55,"defense":90,"special-attack":130,"special-defense":81,"speed":86},"raidMoves":["power-gem","sludge-wave","hyper-beam","rock-polish"],"types":["rock","poison"],"moveInfo":[{"name":"power-gem","power":80,"type":"rock","class":"special"},{"name":"sludge-wave","power":95,"type":"poison","class":"special"},{"name":"hyper-beam","power":150,"type":"normal","class":"special"},{"name":"rock-polish","power":null,"type":"rock","class":"status"}]},{"id":975,"name":"cetitan","stats":{"hp":170,"attack":113,"defense":65,"special-attack":45,"special-defense":55,"speed":73},"raidMoves":["ice-spinner","body-slam","snowscape","stomping-tantrum"],"types":["ice"],"moveInfo":[{"name":"ice-spinner","power":80,"type":"ice","class":"physical"},{"name":"body-slam","power":85,"type":"normal","class":"physical"},{"name":"snowscape","power":0,"type":"ice","class":"status"},{"name":"stomping-tantrum","power":75,"type":"ground","class":"physical"}]},{"id":977,"name":"dondozo","stats":{"hp":150,"attack":100,"defense":115,"special-attack":65,"special-defense":65,"speed":35},"raidMoves":["wave-crash","order-up","heavy-slam","yawn"],"types":["water"],"moveInfo":[{"name":"wave-crash","power":120,"type":"water","class":"physical"},{"name":"order-up","power":80,"type":"dragon","class":"physical"},{"name":"heavy-slam","power":null,"type":"steel","class":"physical"},{"name":"yawn","power":null,"type":"normal","class":"status"}]},{"id":979,"name":"annihilape","stats":{"hp":110,"attack":115,"defense":80,"special-attack":50,"special-defense":90,"speed":90},"raidMoves":["close-combat","shadow-claw","assurance","focus-energy"],"types":["fighting","ghost"],"moveInfo":[{"name":"close-combat","power":120,"type":"fighting","class":"physical"},{"name":"shadow-claw","power":70,"type":"ghost","class":"physical"},{"name":"assurance","power":60,"type":"dark","class":"physical"},{"name":"focus-energy","power":null,"type":"normal","class":"status"}]},{"id":980,"name":"clodsire","stats":{"hp":130,"attack":75,"defense":60,"special-attack":45,"special-defense":100,"speed":20},"raidMoves":["earthquake","poison-jab","megahorn","yawn"],"types":["poison","ground"],"moveInfo":[{"name":"earthquake","power":100,"type":"ground","class":"physical"},{"name":"poison-jab","power":80,"type":"poison","class":"physical"},{"name":"megahorn","power":120,"type":"bug","class":"physical"},{"name":"yawn","power":null,"type":"normal","class":"status"}]},{"id":981,"name":"farigiraf","stats":{"hp":120,"attack":90,"defense":70,"special-attack":110,"special-defense":70,"speed":60},"raidMoves":["twin-beam","hyper-voice","low-kick","uproar"],"types":["normal","psychic"],"moveInfo":[{"name":"twin-beam","power":40,"type":"psychic","class":"special"},{"name":"hyper-voice","power":90,"type":"normal","class":"special"},{"name":"low-kick","power":null,"type":"fighting","class":"physical"},{"name":"uproar","power":90,"type":"normal","class":"special"}]},{"id":983,"name":"kingambit","stats":{"hp":100,"attack":135,"defense":120,"special-attack":60,"special-defense":85,"speed":50},"raidMoves":["iron-head","night-slash","kowtow-cleave","thunder-wave"],"types":["dark","steel"],"moveInfo":[{"name":"iron-head","power":80,"type":"steel","class":"physical"},{"name":"night-slash","power":70,"type":"dark","class":"physical"},{"name":"kowtow-cleave","power":85,"type":"dark","class":"physical"},{"name":"thunder-wave","power":null,"type":"electric","class":"status"}]},{"id":998,"name":"baxcalibur","stats":{"hp":115,"attack":145,"defense":92,"special-attack":75,"special-defense":86,"speed":87},"raidMoves":["icicle-spear","dragon-rush","snowscape","body-press"],"types":["dragon","ice"],"moveInfo":[{"name":"icicle-spear","power":25,"type":"ice","class":"physical"},{"name":"dragon-rush","power":100,"type":"dragon","class":"physical"},{"name":"snowscape","power":0,"type":"ice","class":"status"},{"name":"body-press","power":80,"type":"fighting","class":"physical"}]}]